<annotation>
    <folder>train</folder>
    <filename>36014.jpg</filename>
    <path>D:\TT100K\data\train\36014.jpg</path>
    <source>
        <database>Unknown</database>
    </source>
    <size>
        <width>2048</width>
        <height>2048</height>
        <depth>3</depth>
    </size>
    <segmented>0</segmented>
    <object>
        <name>ip</name>
        <pose>Unspecified</pose>
        <truncated>0</truncated>
        <difficult>0</difficult>
        <bndbox>
            <xmin>1350</xmin>
            <ymin>957</ymin>
            <xmax>1393</xmax>
            <ymax>999</ymax>
        </bndbox>
    </object>
    <object>
        <name>pl60</name>
        <pose>Unspecified</pose>
        <truncated>0</truncated>
        <difficult>0</difficult>
        <bndbox>
            <xmin>1660</xmin>
            <ymin>948</ymin>
            <xmax>1693</xmax>
            <ymax>985</ymax>
        </bndbox>
    </object>
    <object>
        <name>pl60</name>
        <pose>Unspecified</pose>
        <truncated>0</truncated>
        <difficult>0</difficult>
        <bndbox>
            <xmin>1862</xmin>
            <ymin>709</ymin>
            <xmax>1902</xmax>
            <ymax>773</ymax>
        </bndbox>
    </object>

</annotation>
