<annotation>
    <folder>test</folder>
    <filename>49537.jpg</filename>
    <path>D:\TT100K\data\test\49537.jpg</path>
    <source>
        <database>Unknown</database>
    </source>
    <size>
        <width>2048</width>
        <height>2048</height>
        <depth>3</depth>
    </size>
    <segmented>0</segmented>
    <object>
        <name>pl5</name>
        <pose>Unspecified</pose>
        <truncated>0</truncated>
        <difficult>0</difficult>
        <bndbox>
            <xmin>608</xmin>
            <ymin>881</ymin>
            <xmax>700</xmax>
            <ymax>977</ymax>
        </bndbox>
    </object>
    <object>
        <name>pl20</name>
        <pose>Unspecified</pose>
        <truncated>0</truncated>
        <difficult>0</difficult>
        <bndbox>
            <xmin>2</xmin>
            <ymin>880</ymin>
            <xmax>47</xmax>
            <ymax>945</ymax>
        </bndbox>
    </object>

</annotation>
