<annotation>
    <folder>train</folder>
    <filename>62799.jpg</filename>
    <path>D:\TT100K\data\train\62799.jpg</path>
    <source>
        <database>Unknown</database>
    </source>
    <size>
        <width>2048</width>
        <height>2048</height>
        <depth>3</depth>
    </size>
    <segmented>0</segmented>
    <object>
        <name>pl50</name>
        <pose>Unspecified</pose>
        <truncated>0</truncated>
        <difficult>0</difficult>
        <bndbox>
            <xmin>1233</xmin>
            <ymin>717</ymin>
            <xmax>1301</xmax>
            <ymax>794</ymax>
        </bndbox>
    </object>
    <object>
        <name>po</name>
        <pose>Unspecified</pose>
        <truncated>0</truncated>
        <difficult>0</difficult>
        <bndbox>
            <xmin>1306</xmin>
            <ymin>723</ymin>
            <xmax>1378</xmax>
            <ymax>799</ymax>
        </bndbox>
    </object>
    <object>
        <name>p11</name>
        <pose>Unspecified</pose>
        <truncated>0</truncated>
        <difficult>0</difficult>
        <bndbox>
            <xmin>1386</xmin>
            <ymin>730</ymin>
            <xmax>1451</xmax>
            <ymax>799</ymax>
        </bndbox>
    </object>

</annotation>
