<annotation>
    <folder>train</folder>
    <filename>6286.jpg</filename>
    <path>D:\TT100K\data\train\6286.jpg</path>
    <source>
        <database>Unknown</database>
    </source>
    <size>
        <width>2048</width>
        <height>2048</height>
        <depth>3</depth>
    </size>
    <segmented>0</segmented>
    <object>
        <name>pl80</name>
        <pose>Unspecified</pose>
        <truncated>0</truncated>
        <difficult>0</difficult>
        <bndbox>
            <xmin>1467</xmin>
            <ymin>912</ymin>
            <xmax>1487</xmax>
            <ymax>934</ymax>
        </bndbox>
    </object>
    <object>
        <name>pn</name>
        <pose>Unspecified</pose>
        <truncated>0</truncated>
        <difficult>0</difficult>
        <bndbox>
            <xmin>1490</xmin>
            <ymin>914</ymin>
            <xmax>1509</xmax>
            <ymax>937</ymax>
        </bndbox>
    </object>

</annotation>
